{
  "placeholderImages": [
    {
      "id": "dashboard-portfolio",
      "description": "A dynamic stock market chart on a screen, representing the virtual portfolio feature.",
      "imageUrl": "https://images.unsplash.com/photo-1611974789855-9c2a0a7236a3?q=80&w=600&h=400&fit=crop",
      "imageHint": "stock market"
    },
    {
      "id": "dashboard-learn",
      "description": "A person studying with a laptop and notebook, representing the learning modules.",
      "imageUrl": "https://media.istockphoto.com/id/1395046095/photo/3d-notes-with-check-mark-completed-task-list-or-checklist-paper-document-or-report-with.jpg?s=1024x1024&w=is&k=20&c=mFOXskKfM8O0bnNO3WuAeRt1VPv0TqbCeevcIpaC3uA=",
      "imageHint": "person studying"
    },
    {
      "id": "dashboard-budget",
      "description": "A person writing in a notebook next to a calculator and piggy bank, representing budgeting.",
      "imageUrl": "https://plus.unsplash.com/premium_photo-1681487814165-018814c29141?q=80&w=600&h=400&fit=crop",
      "imageHint": "personal finance"
    },
    {
      "id": "dashboard-fraud",
      "description": "A padlock on a digital screen, symbolizing fraud protection and cybersecurity.",
      "imageUrl": "https://images.unsplash.com/photo-1550751827-4bd374c3f58b?q=80&w=600&h=400&fit=crop",
      "imageHint": "cyber security"
    }
  ]
}
